
{"items":[{"name":"QsNet","href":"QsNet.html","topicHref":"QsNet.html","topicUid":"QsNet","type":"Namespace","items":[{"name":"Extensions","href":"QsNet.Extensions.html","topicHref":"QsNet.Extensions.html","topicUid":"QsNet.Extensions","type":"Class"},{"name":"Qs","href":"QsNet.Qs.html","topicHref":"QsNet.Qs.html","topicUid":"QsNet.Qs","type":"Class"}]},{"name":"QsNet.Constants","href":"QsNet.Constants.html","topicHref":"QsNet.Constants.html","topicUid":"QsNet.Constants","type":"Namespace","items":[{"name":"HexTable","href":"QsNet.Constants.HexTable.html","topicHref":"QsNet.Constants.HexTable.html","topicUid":"QsNet.Constants.HexTable","type":"Class"}]},{"name":"QsNet.Enums","href":"QsNet.Enums.html","topicHref":"QsNet.Enums.html","topicUid":"QsNet.Enums","type":"Namespace","items":[{"name":"DecodeKind","href":"QsNet.Enums.DecodeKind.html","topicHref":"QsNet.Enums.DecodeKind.html","topicUid":"QsNet.Enums.DecodeKind","type":"Enum"},{"name":"Duplicates","href":"QsNet.Enums.Duplicates.html","topicHref":"QsNet.Enums.Duplicates.html","topicUid":"QsNet.Enums.Duplicates","type":"Enum"},{"name":"Format","href":"QsNet.Enums.Format.html","topicHref":"QsNet.Enums.Format.html","topicUid":"QsNet.Enums.Format","type":"Enum"},{"name":"FormatExtensions","href":"QsNet.Enums.FormatExtensions.html","topicHref":"QsNet.Enums.FormatExtensions.html","topicUid":"QsNet.Enums.FormatExtensions","type":"Class"},{"name":"Formatter","href":"QsNet.Enums.Formatter.html","topicHref":"QsNet.Enums.Formatter.html","topicUid":"QsNet.Enums.Formatter","type":"Delegate"},{"name":"ListFormat","href":"QsNet.Enums.ListFormat.html","topicHref":"QsNet.Enums.ListFormat.html","topicUid":"QsNet.Enums.ListFormat","type":"Enum"},{"name":"ListFormatExtensions","href":"QsNet.Enums.ListFormatExtensions.html","topicHref":"QsNet.Enums.ListFormatExtensions.html","topicUid":"QsNet.Enums.ListFormatExtensions","type":"Class"},{"name":"ListFormatGenerator","href":"QsNet.Enums.ListFormatGenerator.html","topicHref":"QsNet.Enums.ListFormatGenerator.html","topicUid":"QsNet.Enums.ListFormatGenerator","type":"Delegate"},{"name":"Sentinel","href":"QsNet.Enums.Sentinel.html","topicHref":"QsNet.Enums.Sentinel.html","topicUid":"QsNet.Enums.Sentinel","type":"Enum"},{"name":"SentinelExtensions","href":"QsNet.Enums.SentinelExtensions.html","topicHref":"QsNet.Enums.SentinelExtensions.html","topicUid":"QsNet.Enums.SentinelExtensions","type":"Class"}]},{"name":"QsNet.Models","href":"QsNet.Models.html","topicHref":"QsNet.Models.html","topicUid":"QsNet.Models","type":"Namespace","items":[{"name":"DateSerializer","href":"QsNet.Models.DateSerializer.html","topicHref":"QsNet.Models.DateSerializer.html","topicUid":"QsNet.Models.DateSerializer","type":"Delegate"},{"name":"DecodeOptions","href":"QsNet.Models.DecodeOptions.html","topicHref":"QsNet.Models.DecodeOptions.html","topicUid":"QsNet.Models.DecodeOptions","type":"Class"},{"name":"Decoder","href":"QsNet.Models.Decoder.html","topicHref":"QsNet.Models.Decoder.html","topicUid":"QsNet.Models.Decoder","type":"Delegate"},{"name":"EncodeOptions","href":"QsNet.Models.EncodeOptions.html","topicHref":"QsNet.Models.EncodeOptions.html","topicUid":"QsNet.Models.EncodeOptions","type":"Class"},{"name":"FunctionFilter","href":"QsNet.Models.FunctionFilter.html","topicHref":"QsNet.Models.FunctionFilter.html","topicUid":"QsNet.Models.FunctionFilter","type":"Class"},{"name":"IDelimiter","href":"QsNet.Models.IDelimiter.html","topicHref":"QsNet.Models.IDelimiter.html","topicUid":"QsNet.Models.IDelimiter","type":"Interface"},{"name":"IFilter","href":"QsNet.Models.IFilter.html","topicHref":"QsNet.Models.IFilter.html","topicUid":"QsNet.Models.IFilter","type":"Interface"},{"name":"IterableFilter","href":"QsNet.Models.IterableFilter.html","topicHref":"QsNet.Models.IterableFilter.html","topicUid":"QsNet.Models.IterableFilter","type":"Class"},{"name":"KindAwareDecoder","href":"QsNet.Models.KindAwareDecoder.html","topicHref":"QsNet.Models.KindAwareDecoder.html","topicUid":"QsNet.Models.KindAwareDecoder","type":"Delegate"},{"name":"RegexDelimiter","href":"QsNet.Models.RegexDelimiter.html","topicHref":"QsNet.Models.RegexDelimiter.html","topicUid":"QsNet.Models.RegexDelimiter","type":"Class"},{"name":"StringDelimiter","href":"QsNet.Models.StringDelimiter.html","topicHref":"QsNet.Models.StringDelimiter.html","topicUid":"QsNet.Models.StringDelimiter","type":"Class"},{"name":"ValueEncoder","href":"QsNet.Models.ValueEncoder.html","topicHref":"QsNet.Models.ValueEncoder.html","topicUid":"QsNet.Models.ValueEncoder","type":"Delegate"}]}],"memberLayout":"SamePage","pdf":false}
